odoo/addons/hr_timesheet_nonpayable/README.rst
odoo/addons/hr_timesheet_nonpayable/__init__.py
odoo/addons/hr_timesheet_nonpayable/__manifest__.py
odoo/addons/hr_timesheet_nonpayable/i18n/es.po
odoo/addons/hr_timesheet_nonpayable/i18n/fr.po
odoo/addons/hr_timesheet_nonpayable/i18n/hr_timesheet_nonpayable.pot
odoo/addons/hr_timesheet_nonpayable/i18n/it.po
odoo/addons/hr_timesheet_nonpayable/models/__init__.py
odoo/addons/hr_timesheet_nonpayable/models/account_analytic_line.py
odoo/addons/hr_timesheet_nonpayable/models/project_project.py
odoo/addons/hr_timesheet_nonpayable/readme/CONTRIBUTORS.rst
odoo/addons/hr_timesheet_nonpayable/readme/DESCRIPTION.rst
odoo/addons/hr_timesheet_nonpayable/readme/USAGE.rst
odoo/addons/hr_timesheet_nonpayable/static/description/icon.png
odoo/addons/hr_timesheet_nonpayable/static/description/index.html
odoo/addons/hr_timesheet_nonpayable/tests/__init__.py
odoo/addons/hr_timesheet_nonpayable/tests/test_hr_timesheet_nonpayable.py
odoo/addons/hr_timesheet_nonpayable/views/account_analytic_line.xml
odoo/addons/hr_timesheet_nonpayable/views/project_project.xml
odoo12_addon_hr_timesheet_nonpayable-12.0.1.0.0.99.dev13.dist-info/METADATA
odoo12_addon_hr_timesheet_nonpayable-12.0.1.0.0.99.dev13.dist-info/WHEEL
odoo12_addon_hr_timesheet_nonpayable-12.0.1.0.0.99.dev13.dist-info/top_level.txt
odoo12_addon_hr_timesheet_nonpayable-12.0.1.0.0.99.dev13.dist-info/RECORD
